shisql.py
hx_mysql-0.1.dist-info/METADATA
hx_mysql-0.1.dist-info/WHEEL
hx_mysql-0.1.dist-info/top_level.txt
hx_mysql-0.1.dist-info/RECORD
