Metadata-Version: 2.1
Name: hx-mysql
Version: 0.1
Summary: 大数据1的小石
Home-page: UNKNOWN
Author: 小石
Author-email: 480523858@qq.com
License: UNKNOWN
Platform: UNKNOWN
